sgraph/__init__.py
sgraph/definitions.py
sgraph/exceptions.py
sgraph/graphdataservice.py
sgraph/metricsapi.py
sgraph/modelapi.py
sgraph/selement.py
sgraph/selementassociation.py
sgraph/sgraph.py
sgraph/sgraph_utils.py
sgraph/algorithms/__init__.py
sgraph/algorithms/generalizer.py
sgraph/algorithms/graphutils.py
sgraph/algorithms/pagerank.py
sgraph/algorithms/selementutils.py
sgraph/algorithms/sgraphanalysis.py
sgraph/algorithms/sgraphfiltering.py
sgraph/algorithms/sgraphmetrics.py
sgraph/attributes/__init__.py
sgraph/attributes/attributequeries.py
sgraph/cli/__init__.py
sgraph/cli/filter.py
sgraph/cli/filter_deps.py
sgraph/cli/modelinfo_prettyprinter.py
sgraph/cli/show_model.py
sgraph/compare/__init__.py
sgraph/compare/attributecomparison.py
sgraph/compare/comparegraphattrs.py
sgraph/compare/compareutils.py
sgraph/compare/modelcompare.py
sgraph/compare/renamedetector.py
sgraph/compare/similarityanalysis.py
sgraph/converters/__init__.py
sgraph/converters/deps_to_xml.py
sgraph/converters/graphml.py
sgraph/converters/graphml_to_xml.py
sgraph/converters/sbom_cyclonedx_generator.py
sgraph/converters/sgraph_json.py
sgraph/converters/sgraph_to_cytoscape.py
sgraph/converters/xml_to_3dforcegraph.py
sgraph/converters/xml_to_deps.py
sgraph/converters/xml_to_dot.py
sgraph/converters/xml_to_graphml.py
sgraph/converters/xml_to_hierarchical_json.py
sgraph/converters/xml_to_json.py
sgraph/converters/xml_to_plantuml.py
sgraph/loader/__init__.py
sgraph/loader/attributeloader.py
sgraph/loader/modelloader.py
sgraph-1.2.4.dist-info/LICENSE
sgraph-1.2.4.dist-info/METADATA
sgraph-1.2.4.dist-info/WHEEL
sgraph-1.2.4.dist-info/top_level.txt
sgraph-1.2.4.dist-info/RECORD
