Metadata-Version: 2.1
Name: sgraph
Version: 1.2.4
Summary: sgraph hierarchic graph data structure, format and algorithms
Home-page: https://github.com/softagram/sgraph
Author: Ville Laitila
Author-email: ville.laitila@softagram.com
License: MIT
Project-URL: Homepage, https://github.com/softagram/sgraph
Project-URL: Documentation, https://softagram.github.io/sgraph/
Project-URL: Source, https://github.com/softagram/sgraph
Project-URL: Bug Tracker, https://github.com/softagram/sgraph/issues
Classifier: License :: OSI Approved :: MIT License
Classifier: Operating System :: OS Independent
Classifier: Programming Language :: Python :: 3
Classifier: Programming Language :: Python :: 3 :: Only
Classifier: Programming Language :: Python :: 3.8
Classifier: Programming Language :: Python :: 3.9
Classifier: Programming Language :: Python :: 3.10
Classifier: Programming Language :: Python :: 3.11
Classifier: Programming Language :: Python :: 3.12
Classifier: Programming Language :: Python :: 3.13
Requires-Python: >=3.8
License-File: LICENSE
Requires-Dist: pandas >=1.5.3
Requires-Dist: lxml >=5.3.0
